gaticos/__init__.py
gaticos/main.py
gaticos-0.5.1.dist-info/entry_points.txt
gaticos-0.5.1.dist-info/WHEEL
gaticos-0.5.1.dist-info/METADATA
gaticos-0.5.1.dist-info/RECORD
